Metadata-Version: 2.1
Name: seabreeze-opentrons
Version: 0.1.1
Summary: Python interface module for Ocean Optics spectrometers. This software is not associated with Ocean Optics. Use it at your own risk. Modified by Michael Carter for use with Amassian Research Group Opentrons.
Home-page: https://github.com/mcarter1239/python-seabreeze
Author: Andreas Poehlmann (modified by Michael Carter)
Author-email: andreas@poehlmann.io (mod: mtcarte4@ncsu.edu)
License: MIT
Platform: UNKNOWN
Classifier: Programming Language :: Python :: 2
Classifier: Programming Language :: Python :: 2.7
Classifier: Programming Language :: Python :: 3
Classifier: Programming Language :: Python :: 3.5
Classifier: Programming Language :: Python :: 3.6
Classifier: Programming Language :: Python :: 3.7
Requires-Dist: future
Requires-Dist: numpy (<1.17) ; python_version < "3.6"
Requires-Dist: numpy (<1.19) ; python_version == "3.6.*"
Requires-Dist: numpy ; python_version >= "3.7"
Provides-Extra: cseabreeze
Provides-Extra: pyseabreeze
Requires-Dist: pyusb (>=1.0) ; extra == 'pyseabreeze'
Requires-Dist: enum34 ; (python_version < "3.4") and extra == 'pyseabreeze'
